chain_of_summaries/__init__.py
chain_of_summaries/index.py
chain_of_summaries/metrics.py
chain_of_summaries/qna.py
chain_of_summaries/summary.py
chain_of_summaries-0.0.6.dist-info/METADATA
chain_of_summaries-0.0.6.dist-info/WHEEL
chain_of_summaries-0.0.6.dist-info/RECORD
