Metadata-Version: 2.4
Name: chain-of-summaries
Version: 0.0.6
Summary: A Python package improving /llms.txt format via iterative summarization.
Project-URL: repository, https://github.com/williambrach/chain-of-summaries
Author-email: William Brach <william.brach@stuba.sk>
Requires-Python: >=3.12
Requires-Dist: black>=25.1.0
Requires-Dist: dspy==2.6.15
Requires-Dist: einops>=0.8.0
Requires-Dist: ipykernel>=6.29.5
Requires-Dist: ipywidgets>=8.1.5
Requires-Dist: litellm>=1.53.4
Requires-Dist: matplotlib>=3.10.0
Requires-Dist: pandas>=2.2.3
Requires-Dist: python-dotenv>=1.0.1
Requires-Dist: ruff>=0.9.4
Requires-Dist: seaborn>=0.13.2
Requires-Dist: sentencepiece>=0.2.0
Requires-Dist: tiktoken>=0.8.0
Requires-Dist: torch>=2.6.0
Requires-Dist: transformers>=4.48.2
